{
    "conversation": [
        {
            "portrait": "sister",
            "text": "So what's next?"
        },
        {
            "portrait": "mc",
            "text": "Go home and chill, I guess. I'm pretty wiped."
        },
        {
            "portrait": "sister",
            "text": "Word, that sounds good."
        },
        {
            "portrait": "mc",
            "text": "Hey, no judgement or anything, but don't you get tired of living at home?"
        },
        {
            "portrait": "sister",
            "text": "Nah, it's working for me. I mostly just lay low and play a lot of games."
        },
        {
            "portrait": "sister",
            "text": "Plus, now that mom's dead I was thinking of turning her room into a home gym. Get on those gains, you know."
        },
        {
            "portrait": "mc",
            "text": "I guess that does sound pretty chill."
        },
        {
            "portrait": "mc",
            "text": "Well, if you ever want to visit, you know where to find me."
        },
        {
            "portrait": "sister",
            "text": "Will do! Good seeing you, sis."
        },
        {
            "portrait": "mc",
            "text": "You too! Talk soon."
        }
    ]
}

